survey/__init__.py
survey/_colors.py
survey/_constants.py
survey/_controls.py
survey/_funnels.py
survey/_graphics.py
survey/_handle.py
survey/_helpers.py
survey/_mutates.py
survey/_printers.py
survey/_routines.py
survey/_searches.py
survey/_stage.py
survey/_system.py
survey/_theme.py
survey/_utils.py
survey/_visuals.py
survey/_widgets.py
survey/_core/__init__.py
survey/_core/_ansi.py
survey/_core/_console.py
survey/_core/_constants.py
survey/_core/_cursor.py
survey/_core/_handle.py
survey/_core/_helpers.py
survey/_core/_intel.py
survey/_core/_io.py
survey/_core/_io_os.py
survey/_core/_io_os_nt.py
survey/_core/_io_os_posix.py
survey/_core/_render.py
survey/_core/_screen.py
survey/_core/_source.py
survey-5.4.1.dist-info/LICENSE
survey-5.4.1.dist-info/METADATA
survey-5.4.1.dist-info/WHEEL
survey-5.4.1.dist-info/top_level.txt
survey-5.4.1.dist-info/RECORD
