Metadata-Version: 2.1
Name: survey
Version: 5.4.1
Summary: A simple library for creating beautiful interactive prompts.
Home-page: https://github.com/Exahilosys/survey
License: MIT
Requires-Python: >=3.7
License-File: LICENSE
Provides-Extra: docs
Requires-Dist: sphinx; extra == "docs"
Requires-Dist: sphinx-rtd-theme; extra == "docs"
Requires-Dist: sphinx-paramlinks; extra == "docs"
Requires-Dist: sphinx-autodoc-typehints<1.25.3; extra == "docs"
